cwantic_computer/__init__.py
cwantic_computer/cwantic_core.cp312-win32.pyd
cwantic_computer-0.1.8.dist-info/licenses/LICENSE
cwantic_computer-0.1.8.dist-info/METADATA
cwantic_computer-0.1.8.dist-info/WHEEL
cwantic_computer-0.1.8.dist-info/top_level.txt
cwantic_computer-0.1.8.dist-info/RECORD
