Metadata-Version: 2.1
Name: cwantic_computer
Version: 0.1.8
Summary: Cwantic's Python Library giving access to MetaPiping and MetaStructure
Author-email: Sébastien Wauquier <sw@cwantic.com>
License: GNU GENERAL PUBLIC LICENSE
Classifier: Operating System :: Microsoft :: Windows
Classifier: Programming Language :: Python :: 3
Classifier: Programming Language :: Python :: Implementation :: CPython
Requires-Python: >=3.8
License-File: LICENSE
Requires-Dist: pythonnet
Requires-Dist: pywin32
